Metadata-Version: 1.0
Name: PS-TIFF-Reader
Version: 0.4
Summary: TIFF FILE READER
Home-page: UNKNOWN
Author: alex
Author-email: alex@parkafm.co.kr
License: UNKNOWN
Platform: UNKNOWN
